pydarn/__init__.py
pydarn/version.py
pydarn/exceptions/__init__.py
pydarn/exceptions/plot_exceptions.py
pydarn/exceptions/radar_exceptions.py
pydarn/exceptions/rtp_exceptions.py
pydarn/exceptions/warning_formatting.py
pydarn/io/__init__.py
pydarn/io/superdarn_io.py
pydarn/plotting/__init__.py
pydarn/plotting/acf.py
pydarn/plotting/color_maps.py
pydarn/plotting/fan.py
pydarn/plotting/grid.py
pydarn/plotting/iq.py
pydarn/plotting/maps.py
pydarn/plotting/power.py
pydarn/plotting/projections.py
pydarn/plotting/rtp.py
pydarn/utils/__init__.py
pydarn/utils/citations.py
pydarn/utils/constants.py
pydarn/utils/conversions.py
pydarn/utils/coordinates.py
pydarn/utils/filters.py
pydarn/utils/general_utils.py
pydarn/utils/geo.py
pydarn/utils/plotting.py
pydarn/utils/range_estimations.py
pydarn/utils/recalculate_elevation.py
pydarn/utils/scan.py
pydarn/utils/superdarn_cpid.py
pydarn/utils/superdarn_radars.py
pydarn/utils/terminator.py
pydarn/utils/virtual_heights.py
pydarn-4.2.dist-info/licenses/LICENSE
pydarn-4.2.dist-info/METADATA
pydarn-4.2.dist-info/WHEEL
pydarn-4.2.dist-info/top_level.txt
pydarn-4.2.dist-info/RECORD
