Metadata-Version: 2.4
Name: pydarn
Version: 4.2
Summary: Data visualization library for SuperDARN data
Home-page: https://pydarn.readthedocs.io/en/latest/
Author: SuperDARN Data Visualization Working Group
Classifier: Development Status :: 5 - Production/Stable
Classifier: License :: OSI Approved :: GNU Lesser General Public License v3 (LGPLv3)
Classifier: Programming Language :: Python
Classifier: Programming Language :: Python :: 3
Classifier: Programming Language :: Python :: 3.8
Classifier: Programming Language :: Python :: 3.9
Classifier: Programming Language :: Python :: 3.10
Classifier: Programming Language :: Python :: 3.11
Classifier: Topic :: Scientific/Engineering :: Physics
Classifier: Topic :: Software Development :: Libraries
Requires-Python: >=3.8
License-File: LICENSE
Requires-Dist: pyyaml
Requires-Dist: numpy
Requires-Dist: matplotlib>=3.7.0
Requires-Dist: aacgmv2
Requires-Dist: pydarnio>=2.0.0
Requires-Dist: scipy<1.15.0
Requires-Dist: cartopy>=0.22.0
Dynamic: license-file
